ovccg/__init__.py
ovccg/ovccg.py
ovccg-0.9.dist-info/LICENSE
ovccg-0.9.dist-info/METADATA
ovccg-0.9.dist-info/WHEEL
ovccg-0.9.dist-info/entry_points.txt
ovccg-0.9.dist-info/top_level.txt
ovccg-0.9.dist-info/RECORD
