Metadata-Version: 2.1
Name: ovccg
Version: 0.9
Summary: OVCCG - OpenVpn client config generator
Home-page: https://dev.metatron.com.pl
Author: Mikolaj Niedbala
Author-email: kontakt@mikolajniedbala.pl
License: GNU Library or Lesser General Public License (LGPL)
Platform: UNKNOWN
Classifier: Programming Language :: Python :: 3
Classifier: Development Status :: 5 - Production/Stable
Classifier: License :: OSI Approved :: GNU Lesser General Public License v3 or later (LGPLv3+)
Classifier: Operating System :: POSIX :: Linux
Requires-Dist: pyyaml (==5.1.2)
Requires-Dist: unidecode (>1.0)
